BBWebFw/BBlazeWeb.py
BBWebFw/FileRenderer.py
BBWebFw/__init__.py
BBWebFw/app.py
BBWebFw/backend.py
BBWebFw/example.py
BlackBlazeFw-0.1.2.5.dist-info/LICENSE
BlackBlazeFw-0.1.2.5.dist-info/METADATA
BlackBlazeFw-0.1.2.5.dist-info/WHEEL
BlackBlazeFw-0.1.2.5.dist-info/top_level.txt
BlackBlazeFw-0.1.2.5.dist-info/RECORD
